ythesis/__init__.py
ythesis-0.1.3.dist-info/LICENSE
ythesis-0.1.3.dist-info/WHEEL
ythesis-0.1.3.dist-info/METADATA
ythesis-0.1.3.dist-info/RECORD
